chuk_mcp_function_server/__init__.py
chuk_mcp_function_server/_version.py
chuk_mcp_function_server/base_server.py
chuk_mcp_function_server/cli.py
chuk_mcp_function_server/config.py
chuk_mcp_function_server/function_filter.py
chuk_mcp_function_server-0.1.1.dist-info/METADATA
chuk_mcp_function_server-0.1.1.dist-info/WHEEL
chuk_mcp_function_server-0.1.1.dist-info/entry_points.txt
chuk_mcp_function_server-0.1.1.dist-info/top_level.txt
chuk_mcp_function_server-0.1.1.dist-info/RECORD
